imgsegmentationmq/__init__.py
imgsegmentationmq/helpingfunctions.py
imgsegmentationmq/means/__init__.py
imgsegmentationmq/means/cmeans.py
imgsegmentationmq/means/helpingfunctionsmeans.py
imgsegmentationmq/means/kmeans.py
imgsegmentationmq/quantiles/__init__.py
imgsegmentationmq/quantiles/cquantile.py
imgsegmentationmq/quantiles/helpingfunctionsquantile.py
imgsegmentationmq/quantiles/kquantile.py
imgsegmentationmq-1.3.0.dist-info/LICENSE.txt
imgsegmentationmq-1.3.0.dist-info/METADATA
imgsegmentationmq-1.3.0.dist-info/WHEEL
imgsegmentationmq-1.3.0.dist-info/top_level.txt
imgsegmentationmq-1.3.0.dist-info/RECORD
