Metadata-Version: 2.1
Name: imgsegmentationmq
Version: 1.3.0
Summary: Image segmentation package
Author: Daniel Díaz-Roncero González
Classifier: Programming Language :: Python :: 3
Classifier: License :: OSI Approved :: MIT License
Classifier: Operating System :: OS Independent
Requires-Python: >=3
License-File: LICENSE.txt
Requires-Dist: numpy
